MANIFEST.in
README.md
setup.cfg
setup.py
tap_webcrm/__init__.py
tap_webcrm/client.py
tap_webcrm/discover.py
tap_webcrm/metadata.py
tap_webcrm/stream.py
tap_webcrm.egg-info/PKG-INFO
tap_webcrm.egg-info/SOURCES.txt
tap_webcrm.egg-info/dependency_links.txt
tap_webcrm.egg-info/entry_points.txt
tap_webcrm.egg-info/requires.txt
tap_webcrm.egg-info/top_level.txt
tap_webcrm/schemas/activity.json
tap_webcrm/schemas/delivery.json
tap_webcrm/schemas/opportunity.json
tap_webcrm/schemas/organisation.json
tap_webcrm/schemas/person.json