Metadata-Version: 2.1
Name: tap-webcrm
Version: 0.1.0
Summary: Singer.io tap for extracting data from WebCRM
Home-page: https://github.com/dreamdata-io/tap-webcrm
Author: Dreamdata
License: MIT
Download-URL: https://github.com/dreamdata-io/tap-webcrm/archive/vv0.1.0.tar.gz
Keywords: singer,io,webcrm,etl,crm
Platform: UNKNOWN
Classifier: Programming Language :: Python :: 3 :: Only
Provides-Extra: test
